{"http://rdaregistry.info/Elements/m/carrierType.en":{"targetUri":"http://rdaregistry.info/Elements/m/P30001","code":308},"http://rdaregistry.info/Elements/m/mediaType.en":{"targetUri":"http://rdaregistry.info/Elements/m/P30002","code":308},"http://rdaregistry.info/Elements/m/modeOfIssuance.en":{"targetUri":"http://rdaregistry.info/Elements/m/P30003","code":308},"http://rdaregistry.info/Elements/m/identifierForManifestation.en":{"targetUri":"http://rdaregistry.info/Elements/m/P30004","code":308},"http://rdaregistry.info/Elements/m/preferredCitation.en":{"targetUri":"http://rdaregistry.info/Elements/m/P30005","code":308},"http://rdaregistry.info/Elements/m/regionalEncoding.en":{"targetUri":"http://rdaregistry.info/Elements/m/P30006","code":308},"http://rdaregistry.info/Elements/m/copyrightDate.en":{"targetUri":"http://rdaregistry.info/Elements/m/P30007","code":308},"http://rdaregistry.info/Elements/m/dateOfDistribution.en":{"targetUri":"http://rdaregistry.info/Elements/m/P30008","code":308},"http://rdaregistry.info/Elements/m/dateOfProduction.en":{"targetUri":"http://rdaregistry.info/Elements/m/P30009","code":308},"http://rdaregistry.info/Elements/m/dateOfManufacture.en":{"targetUri":"http://rdaregistry.info/Elements/m/P30010","code":308},"http://rdaregistry.info/Elements/m/dateOfPublication.en":{"targetUri":"http://rdaregistry.info/Elements/m/P30011","code":308},"http://rdaregistry.info/Elements/m/parallelDesignationOfNamedRevisionOfEdition.en":{"targetUri":"http://rdaregistry.info/Elements/m/P30012","code":308},"http://rdaregistry.info/Elements/m/parallelDesignationOfEdition.en":{"targetUri":"http://rdaregistry.info/Elements/m/P30013","code":308},"http://rdaregistry.info/Elements/m/numberingWithinSeries.en":{"targetUri":"http://rdaregistry.info/Elements/m/P30014","code":308},"http://rdaregistry.info/Elements/m/numberingWithinSubseries.en":{"targetUri":"http://rdaregistry.info/Elements/m/P30015","code":308},"http://rdaregistry.info/Elements/m/electronicReproductionManifestation.en":{"targetUri":"http://rdaregistry.info/Elements/m/P30016","code":308},"http://rdaregistry.info/Elements/m/parallelDistributorsName.en":{"targetUri":"http://rdaregistry.info/Elements/m/P30017","code":308},"http://rdaregistry.info/Elements/m/fileType.en":{"targetUri":"http://rdaregistry.info/Elements/m/P30018","code":308},"http://rdaregistry.info/Elements/m/facsimileContainedIn.en":{"targetUri":"http://rdaregistry.info/Elements/m/P30019","code":308},"http://rdaregistry.info/Elements/m/containedInManifestation.en":{"targetUri":"http://rdaregistry.info/Elements/m/P30020","code":308},"http://rdaregistry.info/Elements/m/preservationFacsimileManifestation.en":{"targetUri":"http://rdaregistry.info/Elements/m/P30021","code":308},"http://rdaregistry.info/Elements/m/insert.en":{"targetUri":"http://rdaregistry.info/Elements/m/P30022","code":308},"http://rdaregistry.info/Elements/m/equivalentManifestation.en":{"targetUri":"http://rdaregistry.info/Elements/m/P30024","code":308},"http://rdaregistry.info/Elements/m/insertedIn.en":{"targetUri":"http://rdaregistry.info/Elements/m/P30025","code":308},"http://rdaregistry.info/Elements/m/alsoIssuedAs.en":{"targetUri":"http://rdaregistry.info/Elements/m/P30026","code":308},"http://rdaregistry.info/Elements/m/accompaniedByManifestation.en":{"targetUri":"http://rdaregistry.info/Elements/m/P30027","code":308},"http://rdaregistry.info/Elements/m/mirrorSite.en":{"targetUri":"http://rdaregistry.info/Elements/m/P30028","code":308},"http://rdaregistry.info/Elements/m/digitalTransferManifestation.en":{"targetUri":"http://rdaregistry.info/Elements/m/P30029","code":308},"http://rdaregistry.info/Elements/m/specialIssue.en":{"targetUri":"http://rdaregistry.info/Elements/m/P30030","code":308},"http://rdaregistry.info/Elements/m/facsimileManifestation.en":{"targetUri":"http://rdaregistry.info/Elements/m/P30031","code":308},"http://rdaregistry.info/Elements/m/containerOfManifestation.en":{"targetUri":"http://rdaregistry.info/Elements/m/P30033","code":308},"http://rdaregistry.info/Elements/m/issuedWith.en":{"targetUri":"http://rdaregistry.info/Elements/m/P30035","code":308},"http://rdaregistry.info/Elements/m/onDiscWithManifestation.en":{"targetUri":"http://rdaregistry.info/Elements/m/P30036","code":308},"http://rdaregistry.info/Elements/m/filmedWithManifestation.en":{"targetUri":"http://rdaregistry.info/Elements/m/P30037","code":308},"http://rdaregistry.info/Elements/m/reprintedAsManifestation.en":{"targetUri":"http://rdaregistry.info/Elements/m/P30038","code":308},"http://rdaregistry.info/Elements/m/reproducedAsManifestation.en":{"targetUri":"http://rdaregistry.info/Elements/m/P30039","code":308},"http://rdaregistry.info/Elements/m/digitalTransferOfManifestation.en":{"targetUri":"http://rdaregistry.info/Elements/m/P30040","code":308},"http://rdaregistry.info/Elements/m/reproductionOfManifestation.en":{"targetUri":"http://rdaregistry.info/Elements/m/P30043","code":308},"http://rdaregistry.info/Elements/m/preservationFacsimileOfManifestation.en":{"targetUri":"http://rdaregistry.info/Elements/m/P30045","code":308},"http://rdaregistry.info/Elements/m/facsimileContainerOf.en":{"targetUri":"http://rdaregistry.info/Elements/m/P30046","code":308},"http://rdaregistry.info/Elements/m/facsimileOfManifestation.en":{"targetUri":"http://rdaregistry.info/Elements/m/P30047","code":308},"http://rdaregistry.info/Elements/m/relatedManifestationManifestation.en":{"targetUri":"http://rdaregistry.info/Elements/m/P30048","code":308},"http://rdaregistry.info/Elements/m/parallelManufacturersName.en":{"targetUri":"http://rdaregistry.info/Elements/m/P30049","code":308},"http://rdaregistry.info/Elements/m/noteOnIssuePartOrIterationUsedAsBasisForIdentificationOfManifestation.en":{"targetUri":"http://rdaregistry.info/Elements/m/P30050","code":308},"http://rdaregistry.info/Elements/m/noteOnChangesInCarrierCharacteristics.en":{"targetUri":"http://rdaregistry.info/Elements/m/P30051","code":308},"http://rdaregistry.info/Elements/m/noteOnDistributionStatement.en":{"targetUri":"http://rdaregistry.info/Elements/m/P30052","code":308},"http://rdaregistry.info/Elements/m/noteOnManufactureStatement.en":{"targetUri":"http://rdaregistry.info/Elements/m/P30053","code":308},"http://rdaregistry.info/Elements/m/noteOnProductionStatement.en":{"targetUri":"http://rdaregistry.info/Elements/m/P30054","code":308},"http://rdaregistry.info/Elements/m/noteOnPublicationStatement.en":{"targetUri":"http://rdaregistry.info/Elements/m/P30055","code":308},"http://rdaregistry.info/Elements/m/noteOnFrequency.en":{"targetUri":"http://rdaregistry.info/Elements/m/P30056","code":308},"http://rdaregistry.info/Elements/m/noteOnStatementOfResponsibility.en":{"targetUri":"http://rdaregistry.info/Elements/m/P30057","code":308},"http://rdaregistry.info/Elements/m/noteOnSeriesStatement.en":{"targetUri":"http://rdaregistry.info/Elements/m/P30058","code":308},"http://rdaregistry.info/Elements/m/noteOnCopyrightDate.en":{"targetUri":"http://rdaregistry.info/Elements/m/P30059","code":308},"http://rdaregistry.info/Elements/m/noteOnDimensionsOfManifestation.en":{"targetUri":"http://rdaregistry.info/Elements/m/P30060","code":308},"http://rdaregistry.info/Elements/m/noteOnExtentOfManifestation.en":{"targetUri":"http://rdaregistry.info/Elements/m/P30061","code":308},"http://rdaregistry.info/Elements/m/noteOnNumberingOfSerials.en":{"targetUri":"http://rdaregistry.info/Elements/m/P30062","code":308},"http://rdaregistry.info/Elements/m/noteOnTitle.en":{"targetUri":"http://rdaregistry.info/Elements/m/P30063","code":308},"http://rdaregistry.info/Elements/m/noteOnEditionStatement.en":{"targetUri":"http://rdaregistry.info/Elements/m/P30064","code":308},"http://rdaregistry.info/Elements/m/publishersNumberForNotatedMusic.en":{"targetUri":"http://rdaregistry.info/Elements/m/P30065","code":308},"http://rdaregistry.info/Elements/m/plateNumberForNotatedMusic.en":{"targetUri":"http://rdaregistry.info/Elements/m/P30066","code":308},"http://rdaregistry.info/Elements/m/broadcaster.en":{"targetUri":"http://rdaregistry.info/Elements/m/P30067","code":308},"http://rdaregistry.info/Elements/m/filmDistributor.en":{"targetUri":"http://rdaregistry.info/Elements/m/P30068","code":308},"http://rdaregistry.info/Elements/m/bookDesigner.en":{"targetUri":"http://rdaregistry.info/Elements/m/P30069","code":308},"http://rdaregistry.info/Elements/m/engraver.en":{"targetUri":"http://rdaregistry.info/Elements/m/P30070","code":308},"http://rdaregistry.info/Elements/m/brailleEmbosser.en":{"targetUri":"http://rdaregistry.info/Elements/m/P30071","code":308},"http://rdaregistry.info/Elements/m/printmaker.en":{"targetUri":"http://rdaregistry.info/Elements/m/P30072","code":308},"http://rdaregistry.info/Elements/m/caster.en":{"targetUri":"http://rdaregistry.info/Elements/m/P30073","code":308},"http://rdaregistry.info/Elements/m/lithographer.en":{"targetUri":"http://rdaregistry.info/Elements/m/P30074","code":308},"http://rdaregistry.info/Elements/m/platemaker.en":{"targetUri":"http://rdaregistry.info/Elements/m/P30075","code":308},"http://rdaregistry.info/Elements/m/etcher.en":{"targetUri":"http://rdaregistry.info/Elements/m/P30076","code":308},"http://rdaregistry.info/Elements/m/collotyper.en":{"targetUri":"http://rdaregistry.info/Elements/m/P30077","code":308},"http://rdaregistry.info/Elements/m/printer.en":{"targetUri":"http://rdaregistry.info/Elements/m/P30078","code":308},"http://rdaregistry.info/Elements/m/otherAgentManifestation.en":{"targetUri":"http://rdaregistry.info/Elements/m/P30079","code":308},"http://rdaregistry.info/Elements/m/distributor.en":{"targetUri":"http://rdaregistry.info/Elements/m/P30080","code":308},"http://rdaregistry.info/Elements/m/producerOfUnpublishedManifestation.en":{"targetUri":"http://rdaregistry.info/Elements/m/P30081","code":308},"http://rdaregistry.info/Elements/m/manufacturer.en":{"targetUri":"http://rdaregistry.info/Elements/m/P30082","code":308},"http://rdaregistry.info/Elements/m/publisher.en":{"targetUri":"http://rdaregistry.info/Elements/m/P30083","code":308},"http://rdaregistry.info/Elements/m/appliedMaterial.en":{"targetUri":"http://rdaregistry.info/Elements/m/P30084","code":308},"http://rdaregistry.info/Elements/m/placeOfDistribution.en":{"targetUri":"http://rdaregistry.info/Elements/m/P30085","code":308},"http://rdaregistry.info/Elements/m/placeOfProduction.en":{"targetUri":"http://rdaregistry.info/Elements/m/P30086","code":308},"http://rdaregistry.info/Elements/m/placeOfManufacture.en":{"targetUri":"http://rdaregistry.info/Elements/m/P30087","code":308},"http://rdaregistry.info/Elements/m/placeOfPublication.en":{"targetUri":"http://rdaregistry.info/Elements/m/P30088","code":308},"http://rdaregistry.info/Elements/m/parallelPlaceOfDistribution.en":{"targetUri":"http://rdaregistry.info/Elements/m/P30089","code":308},"http://rdaregistry.info/Elements/m/parallelPlaceOfManufacture.en":{"targetUri":"http://rdaregistry.info/Elements/m/P30090","code":308},"http://rdaregistry.info/Elements/m/parallelPlaceOfProduction.en":{"targetUri":"http://rdaregistry.info/Elements/m/P30091","code":308},"http://rdaregistry.info/Elements/m/parallelPlaceOfPublication.en":{"targetUri":"http://rdaregistry.info/Elements/m/P30092","code":308},"http://rdaregistry.info/Elements/m/reprintOfManifestation.en":{"targetUri":"http://rdaregistry.info/Elements/m/P30093","code":308},"http://rdaregistry.info/Elements/m/parallelProducersName.en":{"targetUri":"http://rdaregistry.info/Elements/m/P30094","code":308},"http://rdaregistry.info/Elements/m/parallelPublishersName.en":{"targetUri":"http://rdaregistry.info/Elements/m/P30095","code":308},"http://rdaregistry.info/Elements/m/encodingFormat.en":{"targetUri":"http://rdaregistry.info/Elements/m/P30096","code":308},"http://rdaregistry.info/Elements/m/alternativeNumericAndOrAlphabeticDesignationOfFirstIssueOrPartOfSequence.en":{"targetUri":"http://rdaregistry.info/Elements/m/P30097","code":308},"http://rdaregistry.info/Elements/m/alternativeNumericAndOrAlphabeticDesignationOfLastIssueOrPartOfSequence.en":{"targetUri":"http://rdaregistry.info/Elements/m/P30098","code":308},"http://rdaregistry.info/Elements/m/alternativeChronologicalDesignationOfFirstIssueOrPartOfSequence.en":{"targetUri":"http://rdaregistry.info/Elements/m/P30099","code":308},"http://rdaregistry.info/Elements/m/alternativeChronologicalDesignationOfLastIssueOrPartOfSequence.en":{"targetUri":"http://rdaregistry.info/Elements/m/P30100","code":308},"http://rdaregistry.info/Elements/m/specialIssueOf.en":{"targetUri":"http://rdaregistry.info/Elements/m/P30101","code":308},"http://rdaregistry.info/Elements/m/digitalRepresentationOfCartographicContent.en":{"targetUri":"http://rdaregistry.info/Elements/m/P30102","code":308},"http://rdaregistry.info/Elements/m/exemplarOfManifestation.en":{"targetUri":"http://rdaregistry.info/Elements/m/P30103","code":308},"http://rdaregistry.info/Elements/m/videoFormat.en":{"targetUri":"http://rdaregistry.info/Elements/m/P30104","code":308},"http://rdaregistry.info/Elements/m/statementOfResponsibilityRelatingToTitleProper.en":{"targetUri":"http://rdaregistry.info/Elements/m/P30105","code":308},"http://rdaregistry.info/Elements/m/seriesStatement.en":{"targetUri":"http://rdaregistry.info/Elements/m/P30106","code":308},"http://rdaregistry.info/Elements/m/editionStatement.en":{"targetUri":"http://rdaregistry.info/Elements/m/P30107","code":308},"http://rdaregistry.info/Elements/m/distributionStatement.en":{"targetUri":"http://rdaregistry.info/Elements/m/P30108","code":308},"http://rdaregistry.info/Elements/m/manufactureStatement.en":{"targetUri":"http://rdaregistry.info/Elements/m/P30109","code":308},"http://rdaregistry.info/Elements/m/productionStatement.en":{"targetUri":"http://rdaregistry.info/Elements/m/P30110","code":308},"http://rdaregistry.info/Elements/m/publicationStatement.en":{"targetUri":"http://rdaregistry.info/Elements/m/P30111","code":308},"http://rdaregistry.info/Elements/m/parallelStatementOfResponsibilityRelatingToNamedRevisionOfEdition.en":{"targetUri":"http://rdaregistry.info/Elements/m/P30112","code":308},"http://rdaregistry.info/Elements/m/parallelStatementOfResponsibilityRelatingToSeries.en":{"targetUri":"http://rdaregistry.info/Elements/m/P30113","code":308},"http://rdaregistry.info/Elements/m/parallelStatementOfResponsibilityRelatingToSubseries.en":{"targetUri":"http://rdaregistry.info/Elements/m/P30114","code":308},"http://rdaregistry.info/Elements/m/parallelStatementOfResponsibilityRelatingToEdition.en":{"targetUri":"http://rdaregistry.info/Elements/m/P30115","code":308},"http://rdaregistry.info/Elements/m/parallelStatementOfResponsibilityRelatingToTitleProper.en":{"targetUri":"http://rdaregistry.info/Elements/m/P30116","code":308},"http://rdaregistry.info/Elements/m/statementOfResponsibility.en":{"targetUri":"http://rdaregistry.info/Elements/m/P30117","code":308},"http://rdaregistry.info/Elements/m/statementOfResponsibilityRelatingToNamedRevisionOfEdition.en":{"targetUri":"http://rdaregistry.info/Elements/m/P30118","code":308},"http://rdaregistry.info/Elements/m/statementOfResponsibilityRelatingToSeries.en":{"targetUri":"http://rdaregistry.info/Elements/m/P30119","code":308},"http://rdaregistry.info/Elements/m/statementOfResponsibilityRelatingToSubseries.en":{"targetUri":"http://rdaregistry.info/Elements/m/P30120","code":308},"http://rdaregistry.info/Elements/m/statementOfResponsibilityRelatingToEdition.en":{"targetUri":"http://rdaregistry.info/Elements/m/P30121","code":308},"http://rdaregistry.info/Elements/m/emulsionOnMicrofilmAndMicrofiche.en":{"targetUri":"http://rdaregistry.info/Elements/m/P30122","code":308},"http://rdaregistry.info/Elements/m/broadcastStandard.en":{"targetUri":"http://rdaregistry.info/Elements/m/P30123","code":308},"http://rdaregistry.info/Elements/m/digitalFileCharacteristic.en":{"targetUri":"http://rdaregistry.info/Elements/m/P30124","code":308},"http://rdaregistry.info/Elements/m/soundCharacteristic.en":{"targetUri":"http://rdaregistry.info/Elements/m/P30125","code":308},"http://rdaregistry.info/Elements/m/videoCharacteristic.en":{"targetUri":"http://rdaregistry.info/Elements/m/P30126","code":308},"http://rdaregistry.info/Elements/m/projectionCharacteristicOfMotionPictureFilm.en":{"targetUri":"http://rdaregistry.info/Elements/m/P30127","code":308},"http://rdaregistry.info/Elements/m/variantTitle.en":{"targetUri":"http://rdaregistry.info/Elements/m/P30128","code":308},"http://rdaregistry.info/Elements/m/laterTitleProper.en":{"targetUri":"http://rdaregistry.info/Elements/m/P30129","code":308},"http://rdaregistry.info/Elements/m/earlierTitleProper.en":{"targetUri":"http://rdaregistry.info/Elements/m/P30130","code":308},"http://rdaregistry.info/Elements/m/abbreviatedTitle.en":{"targetUri":"http://rdaregistry.info/Elements/m/P30131","code":308},"http://rdaregistry.info/Elements/m/designationOfNamedRevisionOfEdition.en":{"targetUri":"http://rdaregistry.info/Elements/m/P30132","code":308},"http://rdaregistry.info/Elements/m/designationOfEdition.en":{"targetUri":"http://rdaregistry.info/Elements/m/P30133","code":308},"http://rdaregistry.info/Elements/m/title.en":{"targetUri":"http://rdaregistry.info/Elements/m/P30134","code":308},"http://rdaregistry.info/Elements/m/workManifested.en":{"targetUri":"http://rdaregistry.info/Elements/m/P30135","code":308},"http://rdaregistry.info/Elements/m/electronicReproductionOfManifestation.en":{"targetUri":"http://rdaregistry.info/Elements/m/P30136","code":308},"http://rdaregistry.info/Elements/m/noteOnManifestation.en":{"targetUri":"http://rdaregistry.info/Elements/m/P30137","code":308},"http://rdaregistry.info/Elements/m/specialPlaybackCharacteristic.en":{"targetUri":"http://rdaregistry.info/Elements/m/P30138","code":308},"http://rdaregistry.info/Elements/m/expressionManifested.en":{"targetUri":"http://rdaregistry.info/Elements/m/P30139","code":308},"http://rdaregistry.info/Elements/m/relatedItemManifestation.en":{"targetUri":"http://rdaregistry.info/Elements/m/P30140","code":308},"http://rdaregistry.info/Elements/m/contactInformation.en":{"targetUri":"http://rdaregistry.info/Elements/m/P30141","code":308},"http://rdaregistry.info/Elements/m/otherTitleInformation.en":{"targetUri":"http://rdaregistry.info/Elements/m/P30142","code":308},"http://rdaregistry.info/Elements/m/otherTitleInformationOfSeries.en":{"targetUri":"http://rdaregistry.info/Elements/m/P30143","code":308},"http://rdaregistry.info/Elements/m/otherTitleInformationOfSubseries.en":{"targetUri":"http://rdaregistry.info/Elements/m/P30144","code":308},"http://rdaregistry.info/Elements/m/restrictionOnAccessToManifestation.en":{"targetUri":"http://rdaregistry.info/Elements/m/P30145","code":308},"http://rdaregistry.info/Elements/m/restrictionOnUseOfManifestation.en":{"targetUri":"http://rdaregistry.info/Elements/m/P30146","code":308},"http://rdaregistry.info/Elements/m/numericAndOrAlphabeticDesignationOfFirstIssueOrPartOfSequence.en":{"targetUri":"http://rdaregistry.info/Elements/m/P30147","code":308},"http://rdaregistry.info/Elements/m/numericAndOrAlphabeticDesignationOfLastIssueOrPartOfSequence.en":{"targetUri":"http://rdaregistry.info/Elements/m/P30148","code":308},"http://rdaregistry.info/Elements/m/chronologicalDesignationOfFirstIssueOrPartOfSequence.en":{"targetUri":"http://rdaregistry.info/Elements/m/P30149","code":308},"http://rdaregistry.info/Elements/m/chronologicalDesignationOfLastIssueOrPartOfSequence.en":{"targetUri":"http://rdaregistry.info/Elements/m/P30150","code":308},"http://rdaregistry.info/Elements/m/parallelOtherTitleInformation.en":{"targetUri":"http://rdaregistry.info/Elements/m/P30151","code":308},"http://rdaregistry.info/Elements/m/parallelOtherTitleInformationOfSeries.en":{"targetUri":"http://rdaregistry.info/Elements/m/P30152","code":308},"http://rdaregistry.info/Elements/m/parallelOtherTitleInformationOfSubseries.en":{"targetUri":"http://rdaregistry.info/Elements/m/P30153","code":308},"http://rdaregistry.info/Elements/m/uniformResourceLocator.en":{"targetUri":"http://rdaregistry.info/Elements/m/P30154","code":308},"http://rdaregistry.info/Elements/m/layout.en":{"targetUri":"http://rdaregistry.info/Elements/m/P30155","code":308},"http://rdaregistry.info/Elements/m/titleProper.en":{"targetUri":"http://rdaregistry.info/Elements/m/P30156","code":308},"http://rdaregistry.info/Elements/m/titleProperOfSeries.en":{"targetUri":"http://rdaregistry.info/Elements/m/P30157","code":308},"http://rdaregistry.info/Elements/m/titleProperOfSubseries.en":{"targetUri":"http://rdaregistry.info/Elements/m/P30158","code":308},"http://rdaregistry.info/Elements/m/resolution.en":{"targetUri":"http://rdaregistry.info/Elements/m/P30159","code":308},"http://rdaregistry.info/Elements/m/termOfAvailability.en":{"targetUri":"http://rdaregistry.info/Elements/m/P30160","code":308},"http://rdaregistry.info/Elements/m/trackConfiguration.en":{"targetUri":"http://rdaregistry.info/Elements/m/P30161","code":308},"http://rdaregistry.info/Elements/m/equipmentOrSystemRequirement.en":{"targetUri":"http://rdaregistry.info/Elements/m/P30162","code":308},"http://rdaregistry.info/Elements/m/presentationFormat.en":{"targetUri":"http://rdaregistry.info/Elements/m/P30163","code":308},"http://rdaregistry.info/Elements/m/grooveCharacteristic.en":{"targetUri":"http://rdaregistry.info/Elements/m/P30164","code":308},"http://rdaregistry.info/Elements/m/numberingOfSerials.en":{"targetUri":"http://rdaregistry.info/Elements/m/P30165","code":308},"http://rdaregistry.info/Elements/m/issnOfSeries.en":{"targetUri":"http://rdaregistry.info/Elements/m/P30166","code":308},"http://rdaregistry.info/Elements/m/issnOfSubseries.en":{"targetUri":"http://rdaregistry.info/Elements/m/P30167","code":308},"http://rdaregistry.info/Elements/m/frequency.en":{"targetUri":"http://rdaregistry.info/Elements/m/P30168","code":308},"http://rdaregistry.info/Elements/m/dimensions.en":{"targetUri":"http://rdaregistry.info/Elements/m/P30169","code":308},"http://rdaregistry.info/Elements/m/dimensionsOfMapEtc.en":{"targetUri":"http://rdaregistry.info/Elements/m/P30170","code":308},"http://rdaregistry.info/Elements/m/dimensionsOfStillImage.en":{"targetUri":"http://rdaregistry.info/Elements/m/P30171","code":308},"http://rdaregistry.info/Elements/m/typeOfRecording.en":{"targetUri":"http://rdaregistry.info/Elements/m/P30172","code":308},"http://rdaregistry.info/Elements/m/distributorsName.en":{"targetUri":"http://rdaregistry.info/Elements/m/P30173","code":308},"http://rdaregistry.info/Elements/m/producersName.en":{"targetUri":"http://rdaregistry.info/Elements/m/P30174","code":308},"http://rdaregistry.info/Elements/m/manufacturersName.en":{"targetUri":"http://rdaregistry.info/Elements/m/P30175","code":308},"http://rdaregistry.info/Elements/m/publishersName.en":{"targetUri":"http://rdaregistry.info/Elements/m/P30176","code":308},"http://rdaregistry.info/Elements/m/extentOfCartographicResource.en":{"targetUri":"http://rdaregistry.info/Elements/m/P30177","code":308},"http://rdaregistry.info/Elements/m/extentOfNotatedMusic.en":{"targetUri":"http://rdaregistry.info/Elements/m/P30178","code":308},"http://rdaregistry.info/Elements/m/extentOfStillImage.en":{"targetUri":"http://rdaregistry.info/Elements/m/P30179","code":308},"http://rdaregistry.info/Elements/m/extentOfThreeDimensionalForm.en":{"targetUri":"http://rdaregistry.info/Elements/m/P30180","code":308},"http://rdaregistry.info/Elements/m/extentOfText.en":{"targetUri":"http://rdaregistry.info/Elements/m/P30181","code":308},"http://rdaregistry.info/Elements/m/extent.en":{"targetUri":"http://rdaregistry.info/Elements/m/P30182","code":308},"http://rdaregistry.info/Elements/m/fileSize.en":{"targetUri":"http://rdaregistry.info/Elements/m/P30183","code":308},"http://rdaregistry.info/Elements/m/configurationOfPlaybackChannels.en":{"targetUri":"http://rdaregistry.info/Elements/m/P30184","code":308},"http://rdaregistry.info/Elements/m/tapeConfiguration.en":{"targetUri":"http://rdaregistry.info/Elements/m/P30185","code":308},"http://rdaregistry.info/Elements/m/mount.en":{"targetUri":"http://rdaregistry.info/Elements/m/P30186","code":308},"http://rdaregistry.info/Elements/m/productionMethod.en":{"targetUri":"http://rdaregistry.info/Elements/m/P30187","code":308},"http://rdaregistry.info/Elements/m/productionMethodForTactileResource.en":{"targetUri":"http://rdaregistry.info/Elements/m/P30188","code":308},"http://rdaregistry.info/Elements/m/productionMethodForManuscript.en":{"targetUri":"http://rdaregistry.info/Elements/m/P30189","code":308},"http://rdaregistry.info/Elements/m/generationOfAudioRecording.en":{"targetUri":"http://rdaregistry.info/Elements/m/P30190","code":308},"http://rdaregistry.info/Elements/m/generation.en":{"targetUri":"http://rdaregistry.info/Elements/m/P30191","code":308},"http://rdaregistry.info/Elements/m/generationOfDigitalResource.en":{"targetUri":"http://rdaregistry.info/Elements/m/P30192","code":308},"http://rdaregistry.info/Elements/m/generationOfMotionPictureFilm.en":{"targetUri":"http://rdaregistry.info/Elements/m/P30193","code":308},"http://rdaregistry.info/Elements/m/generationOfVideotape.en":{"targetUri":"http://rdaregistry.info/Elements/m/P30194","code":308},"http://rdaregistry.info/Elements/m/generationOfMicroform.en":{"targetUri":"http://rdaregistry.info/Elements/m/P30195","code":308},"http://rdaregistry.info/Elements/m/polarity.en":{"targetUri":"http://rdaregistry.info/Elements/m/P30196","code":308},"http://rdaregistry.info/Elements/m/bibliographicFormat.en":{"targetUri":"http://rdaregistry.info/Elements/m/P30197","code":308},"http://rdaregistry.info/Elements/m/reductionRatio.en":{"targetUri":"http://rdaregistry.info/Elements/m/P30198","code":308},"http://rdaregistry.info/Elements/m/fontSize.en":{"targetUri":"http://rdaregistry.info/Elements/m/P30199","code":308},"http://rdaregistry.info/Elements/m/projectionSpeed.en":{"targetUri":"http://rdaregistry.info/Elements/m/P30200","code":308},"http://rdaregistry.info/Elements/m/playingSpeed.en":{"targetUri":"http://rdaregistry.info/Elements/m/P30201","code":308},"http://rdaregistry.info/Elements/m/encodedBitrate.en":{"targetUri":"http://rdaregistry.info/Elements/m/P30202","code":308},"http://rdaregistry.info/Elements/m/parallelTitleProper.en":{"targetUri":"http://rdaregistry.info/Elements/m/P30203","code":308},"http://rdaregistry.info/Elements/m/parallelTitleProperOfSeries.en":{"targetUri":"http://rdaregistry.info/Elements/m/P30204","code":308},"http://rdaregistry.info/Elements/m/parallelTitleProperOfSubseries.en":{"targetUri":"http://rdaregistry.info/Elements/m/P30205","code":308},"http://rdaregistry.info/Elements/m/recordingMedium.en":{"targetUri":"http://rdaregistry.info/Elements/m/P30206","code":308},"http://rdaregistry.info/Elements/m/baseMaterial.en":{"targetUri":"http://rdaregistry.info/Elements/m/P30208","code":308},"http://rdaregistry.info/Elements/m/keyTitle.en":{"targetUri":"http://rdaregistry.info/Elements/m/P30209","code":308},"http://rdaregistry.info/Elements/m/accompanyingManifestationRelationship.en":{"targetUri":"http://rdaregistry.info/Elements/m/P30210","code":308},"http://rdaregistry.info/Elements/m/equivalentManifestationRelationship.en":{"targetUri":"http://rdaregistry.info/Elements/m/P30212","code":308},"http://rdaregistry.info/Elements/m/wholePartManifestationRelationship.en":{"targetUri":"http://rdaregistry.info/Elements/m/P30213","code":308},"http://rdaregistry.info/Elements/m/noteOnCarrier.en":{"targetUri":"http://rdaregistry.info/Elements/m/P30214","code":308},"http://rdaregistry.info/Elements/m/papermaker.en":{"targetUri":"http://rdaregistry.info/Elements/m/P30215","code":308},"http://rdaregistry.info/Elements/m/detailsOfAppliedMaterial.en":{"targetUri":"http://rdaregistry.info/Elements/m/P30216","code":308},"http://rdaregistry.info/Elements/m/detailsOfBaseMaterial.en":{"targetUri":"http://rdaregistry.info/Elements/m/P30217","code":308},"http://rdaregistry.info/Elements/m/detailsOfBibliographicFormat.en":{"targetUri":"http://rdaregistry.info/Elements/m/P30218","code":308},"http://rdaregistry.info/Elements/m/detailsOfBroadcastStandard.en":{"targetUri":"http://rdaregistry.info/Elements/m/P30219","code":308},"http://rdaregistry.info/Elements/m/detailsOfConfigurationOfPlaybackChannels.en":{"targetUri":"http://rdaregistry.info/Elements/m/P30220","code":308},"http://rdaregistry.info/Elements/m/detailsOfDigitalFileCharacteristic.en":{"targetUri":"http://rdaregistry.info/Elements/m/P30221","code":308},"http://rdaregistry.info/Elements/m/detailsOfDigitalRepresentationOfCartographicContent.en":{"targetUri":"http://rdaregistry.info/Elements/m/P30222","code":308},"http://rdaregistry.info/Elements/m/detailsOfEmulsionOnMicrofilmAndMicrofiche.en":{"targetUri":"http://rdaregistry.info/Elements/m/P30223","code":308},"http://rdaregistry.info/Elements/m/detailsOfEncodingFormat.en":{"targetUri":"http://rdaregistry.info/Elements/m/P30224","code":308},"http://rdaregistry.info/Elements/m/detailsOfFileType.en":{"targetUri":"http://rdaregistry.info/Elements/m/P30225","code":308},"http://rdaregistry.info/Elements/m/detailsOfFontSize.en":{"targetUri":"http://rdaregistry.info/Elements/m/P30226","code":308},"http://rdaregistry.info/Elements/m/detailsOfGenerationOfAudioRecording.en":{"targetUri":"http://rdaregistry.info/Elements/m/P30227","code":308},"http://rdaregistry.info/Elements/m/detailsOfGenerationOfDigitalResource.en":{"targetUri":"http://rdaregistry.info/Elements/m/P30228","code":308},"http://rdaregistry.info/Elements/m/detailsOfGenerationOfMicroform.en":{"targetUri":"http://rdaregistry.info/Elements/m/P30229","code":308},"http://rdaregistry.info/Elements/m/detailsOfGenerationOfMotionPictureFilm.en":{"targetUri":"http://rdaregistry.info/Elements/m/P30230","code":308},"http://rdaregistry.info/Elements/m/detailsOfGenerationOfVideotape.en":{"targetUri":"http://rdaregistry.info/Elements/m/P30231","code":308},"http://rdaregistry.info/Elements/m/detailsOfGrooveCharacteristic.en":{"targetUri":"http://rdaregistry.info/Elements/m/P30232","code":308},"http://rdaregistry.info/Elements/m/detailsOfLayout.en":{"targetUri":"http://rdaregistry.info/Elements/m/P30233","code":308},"http://rdaregistry.info/Elements/m/detailsOfMount.en":{"targetUri":"http://rdaregistry.info/Elements/m/P30234","code":308},"http://rdaregistry.info/Elements/m/detailsOfPlayingSpeed.en":{"targetUri":"http://rdaregistry.info/Elements/m/P30235","code":308},"http://rdaregistry.info/Elements/m/detailsOfPolarity.en":{"targetUri":"http://rdaregistry.info/Elements/m/P30236","code":308},"http://rdaregistry.info/Elements/m/detailsOfPresentationFormat.en":{"targetUri":"http://rdaregistry.info/Elements/m/P30237","code":308},"http://rdaregistry.info/Elements/m/detailsOfProductionMethod.en":{"targetUri":"http://rdaregistry.info/Elements/m/P30238","code":308},"http://rdaregistry.info/Elements/m/detailsOfProductionMethodForManuscript.en":{"targetUri":"http://rdaregistry.info/Elements/m/P30239","code":308},"http://rdaregistry.info/Elements/m/detailsOfProductionMethodForTactileResource.en":{"targetUri":"http://rdaregistry.info/Elements/m/P30240","code":308},"http://rdaregistry.info/Elements/m/detailsOfProjectionCharacteristicOfMotionPictureFilm.en":{"targetUri":"http://rdaregistry.info/Elements/m/P30241","code":308},"http://rdaregistry.info/Elements/m/detailsOfProjectionSpeed.en":{"targetUri":"http://rdaregistry.info/Elements/m/P30242","code":308},"http://rdaregistry.info/Elements/m/detailsOfRecordingMedium.en":{"targetUri":"http://rdaregistry.info/Elements/m/P30243","code":308},"http://rdaregistry.info/Elements/m/detailsOfReductionRatioDesignation.en":{"targetUri":"http://rdaregistry.info/Elements/m/P30244","code":308},"http://rdaregistry.info/Elements/m/detailsOfSoundCharacteristic.en":{"targetUri":"http://rdaregistry.info/Elements/m/P30245","code":308},"http://rdaregistry.info/Elements/m/detailsOfSpecialPlaybackCharacteristic.en":{"targetUri":"http://rdaregistry.info/Elements/m/P30246","code":308},"http://rdaregistry.info/Elements/m/detailsOfTapeConfiguration.en":{"targetUri":"http://rdaregistry.info/Elements/m/P30247","code":308},"http://rdaregistry.info/Elements/m/detailsOfTrackConfiguration.en":{"targetUri":"http://rdaregistry.info/Elements/m/P30248","code":308},"http://rdaregistry.info/Elements/m/detailsOfTypeOfRecording.en":{"targetUri":"http://rdaregistry.info/Elements/m/P30249","code":308},"http://rdaregistry.info/Elements/m/detailsOfVideoCharacteristic.en":{"targetUri":"http://rdaregistry.info/Elements/m/P30250","code":308},"http://rdaregistry.info/Elements/m/detailsOfVideoFormat.en":{"targetUri":"http://rdaregistry.info/Elements/m/P30251","code":308},"http://rdaregistry.info/Elements/m/detailsOfGeneration.en":{"targetUri":"http://rdaregistry.info/Elements/m/P30252","code":308},"http://rdaregistry.info/Elements/m/subjectOfManifestation.en":{"targetUri":"http://rdaregistry.info/Elements/m/P30253","code":308},"http://rdaregistry.info/Elements/m/describedInManifestation.en":{"targetUri":"http://rdaregistry.info/Elements/m/P30254","code":308},"http://rdaregistry.info/Elements/m/analysedInManifestation.en":{"targetUri":"http://rdaregistry.info/Elements/m/P30255","code":308},"http://rdaregistry.info/Elements/m/commentaryInManifestation.en":{"targetUri":"http://rdaregistry.info/Elements/m/P30256","code":308},"http://rdaregistry.info/Elements/m/critiquedInManifestation.en":{"targetUri":"http://rdaregistry.info/Elements/m/P30257","code":308},"http://rdaregistry.info/Elements/m/evaluatedInManifestation.en":{"targetUri":"http://rdaregistry.info/Elements/m/P30258","code":308},"http://rdaregistry.info/Elements/m/reviewedInManifestation.en":{"targetUri":"http://rdaregistry.info/Elements/m/P30259","code":308},"http://rdaregistry.info/Elements/m/noteOnIdentifierForManifestation.en":{"targetUri":"http://rdaregistry.info/Elements/m/P30260","code":308},"http://rdaregistry.info/Elements/m/cartographicDataType.en":{"targetUri":"http://rdaregistry.info/Elements/m/P30261","code":308},"http://rdaregistry.info/Elements/m/detailsOfCartographicDataType.en":{"targetUri":"http://rdaregistry.info/Elements/m/P30262","code":308},"http://rdaregistry.info/Elements/m/reductionRatioDesignation.en":{"targetUri":"http://rdaregistry.info/Elements/m/P30263","code":308},"http://rdaregistry.info/Elements/m/relatedEntityManifestation.en":{"targetUri":"http://rdaregistry.info/Elements/m/P30264","code":308},"http://rdaregistry.info/Elements/m/relatedWorkManifestation.en":{"targetUri":"http://rdaregistry.info/Elements/m/P30265","code":308},"http://rdaregistry.info/Elements/m/relatedExpressionManifestation.en":{"targetUri":"http://rdaregistry.info/Elements/m/P30266","code":308},"http://rdaregistry.info/Elements/m/relatedAgentManifestation.en":{"targetUri":"http://rdaregistry.info/Elements/m/P30267","code":308},"http://rdaregistry.info/Elements/m/relatedPersonManifestation.en":{"targetUri":"http://rdaregistry.info/Elements/m/P30268","code":308},"http://rdaregistry.info/Elements/m/relatedFamilyManifestation.en":{"targetUri":"http://rdaregistry.info/Elements/m/P30269","code":308},"http://rdaregistry.info/Elements/m/relatedCorporateBodyManifestation.en":{"targetUri":"http://rdaregistry.info/Elements/m/P30270","code":308},"http://rdaregistry.info/Elements/m/relatedCollectiveAgentManifestation.en":{"targetUri":"http://rdaregistry.info/Elements/m/P30271","code":308},"http://rdaregistry.info/Elements/m/relatedPlaceManifestation.en":{"targetUri":"http://rdaregistry.info/Elements/m/P30272","code":308},"http://rdaregistry.info/Elements/m/relatedTimespanManifestation.en":{"targetUri":"http://rdaregistry.info/Elements/m/P30273","code":308},"http://rdaregistry.info/Elements/m/relatedNomenManifestation.en":{"targetUri":"http://rdaregistry.info/Elements/m/P30274","code":308},"http://rdaregistry.info/Elements/m/detailsOfRegionalEncoding.en":{"targetUri":"http://rdaregistry.info/Elements/m/P30275","code":308}}