<?xml version="1.0" encoding="UTF-8"?><rdf:RDF
    xml:base="http://rdaregistry.info/Elements/x/datatype/"
    xmlns:dc="http://purl.org/dc/elements/1.1/"
    xmlns:foaf="http://xmlns.com/foaf/0.1/"
    xmlns:rdf="http://www.w3.org/1999/02/22-rdf-syntax-ns#"
    xmlns:rdfs="http://www.w3.org/2000/01/rdf-schema#"
    xmlns:reg="http://metadataregistry.org/uri/profile/regap/"
    xmlns:skos="http://www.w3.org/2004/02/skos/core#">

<!-- Element Set: RDA Entity datatype properties -->
<rdf:Description rdf:about="http://rdaregistry.info/Elements/x/datatype/">
  <dc:title xml:lang="en">RDA Entity datatype properties</dc:title>
</rdf:Description>

<!-- Properties -->

<!-- Property: has related agent -->
<rdf:Description rdf:about="http://rdaregistry.info/Elements/x/datatype/P00006">
  <rdfs:isDefinedBy rdf:resource="http://rdaregistry.info/Elements/x/datatype/" />
  <reg:status rdf:resource="http://metadataregistry.org/uri/RegStatus/1001" />
  <rdfs:subPropertyOf rdf:resource="http://rdaregistry.info/Elements/x/P00006" />
  <rdf:type rdf:resource="http://www.w3.org/1999/02/22-rdf-syntax-ns#Property" />
  <reg:name xml:lang="en">relatedAgent</reg:name>
  <rdfs:label xml:lang="en">has related agent</rdfs:label>
  <reg:lexicalAlias rdf:resource="http://rdaregistry.info/Elements/x/datatype/relatedAgent.en" />
  <rdfs:domain rdf:resource="http://rdaregistry.info/Elements/c/C10013" />
  <rdfs:subPropertyOf rdf:resource="http://rdaregistry.info/Elements/x/datatype/P00001" />
</rdf:Description>

<!-- Property: has related collective agent -->
<rdf:Description rdf:about="http://rdaregistry.info/Elements/x/datatype/P00012">
  <rdfs:isDefinedBy rdf:resource="http://rdaregistry.info/Elements/x/datatype/" />
  <reg:status rdf:resource="http://metadataregistry.org/uri/RegStatus/1001" />
  <rdfs:subPropertyOf rdf:resource="http://rdaregistry.info/Elements/x/P00012" />
  <rdf:type rdf:resource="http://www.w3.org/1999/02/22-rdf-syntax-ns#Property" />
  <reg:name xml:lang="en">relatedCollectiveAgent</reg:name>
  <rdfs:label xml:lang="en">has related collective agent</rdfs:label>
  <reg:lexicalAlias rdf:resource="http://rdaregistry.info/Elements/x/datatype/relatedCollectiveAgent.en" />
  <rdfs:domain rdf:resource="http://rdaregistry.info/Elements/c/C10013" />
  <rdfs:subPropertyOf rdf:resource="http://rdaregistry.info/Elements/x/datatype/P00006" />
</rdf:Description>

<!-- Property: has related corporate body -->
<rdf:Description rdf:about="http://rdaregistry.info/Elements/x/datatype/P00009">
  <rdfs:isDefinedBy rdf:resource="http://rdaregistry.info/Elements/x/datatype/" />
  <reg:status rdf:resource="http://metadataregistry.org/uri/RegStatus/1001" />
  <rdfs:subPropertyOf rdf:resource="http://rdaregistry.info/Elements/x/P00009" />
  <rdf:type rdf:resource="http://www.w3.org/1999/02/22-rdf-syntax-ns#Property" />
  <reg:name xml:lang="en">relatedCorporateBody</reg:name>
  <rdfs:label xml:lang="en">has related corporate body</rdfs:label>
  <reg:lexicalAlias rdf:resource="http://rdaregistry.info/Elements/x/datatype/relatedCorporateBody.en" />
  <rdfs:domain rdf:resource="http://rdaregistry.info/Elements/c/C10013" />
  <rdfs:subPropertyOf rdf:resource="http://rdaregistry.info/Elements/x/datatype/P00012" />
</rdf:Description>

<!-- Property: has related entity -->
<rdf:Description rdf:about="http://rdaregistry.info/Elements/x/datatype/P00001">
  <rdfs:isDefinedBy rdf:resource="http://rdaregistry.info/Elements/x/datatype/" />
  <reg:status rdf:resource="http://metadataregistry.org/uri/RegStatus/1001" />
  <rdfs:label xml:lang="en">has related entity</rdfs:label>
  <rdf:type rdf:resource="http://www.w3.org/1999/02/22-rdf-syntax-ns#Property" />
  <reg:name xml:lang="en">relatedEntity</reg:name>
  <reg:lexicalAlias rdf:resource="http://rdaregistry.info/Elements/x/datatype/relatedEntity.en" />
  <rdfs:subPropertyOf rdf:resource="http://rdaregistry.info/Elements/x/P00001" />
  <rdfs:domain rdf:resource="http://rdaregistry.info/Elements/c/C10013" />
</rdf:Description>

<!-- Property: has related expression -->
<rdf:Description rdf:about="http://rdaregistry.info/Elements/x/datatype/P00003">
  <rdfs:isDefinedBy rdf:resource="http://rdaregistry.info/Elements/x/datatype/" />
  <reg:status rdf:resource="http://metadataregistry.org/uri/RegStatus/1001" />
  <rdfs:subPropertyOf rdf:resource="http://rdaregistry.info/Elements/x/P00003" />
  <rdf:type rdf:resource="http://www.w3.org/1999/02/22-rdf-syntax-ns#Property" />
  <reg:name xml:lang="en">relatedExpression</reg:name>
  <rdfs:label xml:lang="en">has related expression</rdfs:label>
  <reg:lexicalAlias rdf:resource="http://rdaregistry.info/Elements/x/datatype/relatedExpression.en" />
  <rdfs:domain rdf:resource="http://rdaregistry.info/Elements/c/C10013" />
  <rdfs:subPropertyOf rdf:resource="http://rdaregistry.info/Elements/x/datatype/P00001" />
</rdf:Description>

<!-- Property: has related family -->
<rdf:Description rdf:about="http://rdaregistry.info/Elements/x/datatype/P00008">
  <rdfs:isDefinedBy rdf:resource="http://rdaregistry.info/Elements/x/datatype/" />
  <reg:status rdf:resource="http://metadataregistry.org/uri/RegStatus/1001" />
  <rdfs:subPropertyOf rdf:resource="http://rdaregistry.info/Elements/x/P00008" />
  <rdf:type rdf:resource="http://www.w3.org/1999/02/22-rdf-syntax-ns#Property" />
  <reg:name xml:lang="en">relatedFamily</reg:name>
  <rdfs:label xml:lang="en">has related family</rdfs:label>
  <reg:lexicalAlias rdf:resource="http://rdaregistry.info/Elements/x/datatype/relatedFamily.en" />
  <rdfs:domain rdf:resource="http://rdaregistry.info/Elements/c/C10013" />
  <rdfs:subPropertyOf rdf:resource="http://rdaregistry.info/Elements/x/datatype/P00012" />
</rdf:Description>

<!-- Property: has related item -->
<rdf:Description rdf:about="http://rdaregistry.info/Elements/x/datatype/P00005">
  <rdfs:isDefinedBy rdf:resource="http://rdaregistry.info/Elements/x/datatype/" />
  <reg:status rdf:resource="http://metadataregistry.org/uri/RegStatus/1001" />
  <rdfs:subPropertyOf rdf:resource="http://rdaregistry.info/Elements/x/P00005" />
  <rdf:type rdf:resource="http://www.w3.org/1999/02/22-rdf-syntax-ns#Property" />
  <reg:name xml:lang="en">relatedItem</reg:name>
  <rdfs:label xml:lang="en">has related item</rdfs:label>
  <reg:lexicalAlias rdf:resource="http://rdaregistry.info/Elements/x/datatype/relatedItem.en" />
  <rdfs:domain rdf:resource="http://rdaregistry.info/Elements/c/C10013" />
  <rdfs:subPropertyOf rdf:resource="http://rdaregistry.info/Elements/x/datatype/P00001" />
</rdf:Description>

<!-- Property: has related manifestation -->
<rdf:Description rdf:about="http://rdaregistry.info/Elements/x/datatype/P00004">
  <rdfs:isDefinedBy rdf:resource="http://rdaregistry.info/Elements/x/datatype/" />
  <reg:status rdf:resource="http://metadataregistry.org/uri/RegStatus/1001" />
  <rdfs:subPropertyOf rdf:resource="http://rdaregistry.info/Elements/x/P00004" />
  <rdf:type rdf:resource="http://www.w3.org/1999/02/22-rdf-syntax-ns#Property" />
  <reg:name xml:lang="en">relatedManifestation</reg:name>
  <rdfs:label xml:lang="en">has related manifestation</rdfs:label>
  <reg:lexicalAlias rdf:resource="http://rdaregistry.info/Elements/x/datatype/relatedManifestation.en" />
  <rdfs:domain rdf:resource="http://rdaregistry.info/Elements/c/C10013" />
  <rdfs:subPropertyOf rdf:resource="http://rdaregistry.info/Elements/x/datatype/P00001" />
</rdf:Description>

<!-- Property: has related nomen -->
<rdf:Description rdf:about="http://rdaregistry.info/Elements/x/datatype/P00013">
  <rdfs:isDefinedBy rdf:resource="http://rdaregistry.info/Elements/x/datatype/" />
  <reg:status rdf:resource="http://metadataregistry.org/uri/RegStatus/1001" />
  <rdfs:subPropertyOf rdf:resource="http://rdaregistry.info/Elements/x/P00013" />
  <rdf:type rdf:resource="http://www.w3.org/1999/02/22-rdf-syntax-ns#Property" />
  <reg:name xml:lang="en">relatedNomen</reg:name>
  <rdfs:label xml:lang="en">has related nomen</rdfs:label>
  <reg:lexicalAlias rdf:resource="http://rdaregistry.info/Elements/x/datatype/relatedNomen.en" />
  <rdfs:domain rdf:resource="http://rdaregistry.info/Elements/c/C10013" />
  <rdfs:subPropertyOf rdf:resource="http://rdaregistry.info/Elements/x/datatype/P00001" />
</rdf:Description>

<!-- Property: has related person -->
<rdf:Description rdf:about="http://rdaregistry.info/Elements/x/datatype/P00007">
  <rdfs:isDefinedBy rdf:resource="http://rdaregistry.info/Elements/x/datatype/" />
  <reg:status rdf:resource="http://metadataregistry.org/uri/RegStatus/1001" />
  <rdfs:subPropertyOf rdf:resource="http://rdaregistry.info/Elements/x/P00007" />
  <rdf:type rdf:resource="http://www.w3.org/1999/02/22-rdf-syntax-ns#Property" />
  <reg:name xml:lang="en">relatedPerson</reg:name>
  <rdfs:label xml:lang="en">has related person</rdfs:label>
  <reg:lexicalAlias rdf:resource="http://rdaregistry.info/Elements/x/datatype/relatedPerson.en" />
  <rdfs:domain rdf:resource="http://rdaregistry.info/Elements/c/C10013" />
  <rdfs:subPropertyOf rdf:resource="http://rdaregistry.info/Elements/x/datatype/P00006" />
</rdf:Description>

<!-- Property: has related place -->
<rdf:Description rdf:about="http://rdaregistry.info/Elements/x/datatype/P00010">
  <rdfs:isDefinedBy rdf:resource="http://rdaregistry.info/Elements/x/datatype/" />
  <reg:status rdf:resource="http://metadataregistry.org/uri/RegStatus/1001" />
  <rdfs:subPropertyOf rdf:resource="http://rdaregistry.info/Elements/x/P00010" />
  <rdf:type rdf:resource="http://www.w3.org/1999/02/22-rdf-syntax-ns#Property" />
  <reg:name xml:lang="en">relatedPlace</reg:name>
  <rdfs:label xml:lang="en">has related place</rdfs:label>
  <reg:lexicalAlias rdf:resource="http://rdaregistry.info/Elements/x/datatype/relatedPlace.en" />
  <rdfs:domain rdf:resource="http://rdaregistry.info/Elements/c/C10013" />
  <rdfs:subPropertyOf rdf:resource="http://rdaregistry.info/Elements/x/datatype/P00001" />
</rdf:Description>

<!-- Property: has related time-span -->
<rdf:Description rdf:about="http://rdaregistry.info/Elements/x/datatype/P00011">
  <rdfs:isDefinedBy rdf:resource="http://rdaregistry.info/Elements/x/datatype/" />
  <reg:status rdf:resource="http://metadataregistry.org/uri/RegStatus/1001" />
  <rdfs:subPropertyOf rdf:resource="http://rdaregistry.info/Elements/x/P00011" />
  <rdf:type rdf:resource="http://www.w3.org/1999/02/22-rdf-syntax-ns#Property" />
  <reg:name xml:lang="en">relatedTimeSpan</reg:name>
  <rdfs:label xml:lang="en">has related time-span</rdfs:label>
  <reg:lexicalAlias rdf:resource="http://rdaregistry.info/Elements/x/datatype/relatedTimeSpan.en" />
  <rdfs:domain rdf:resource="http://rdaregistry.info/Elements/c/C10013" />
  <rdfs:subPropertyOf rdf:resource="http://rdaregistry.info/Elements/x/datatype/P00001" />
</rdf:Description>

<!-- Property: has related work -->
<rdf:Description rdf:about="http://rdaregistry.info/Elements/x/datatype/P00002">
  <rdfs:isDefinedBy rdf:resource="http://rdaregistry.info/Elements/x/datatype/" />
  <reg:status rdf:resource="http://metadataregistry.org/uri/RegStatus/1001" />
  <rdfs:subPropertyOf rdf:resource="http://rdaregistry.info/Elements/x/P00002" />
  <rdf:type rdf:resource="http://www.w3.org/1999/02/22-rdf-syntax-ns#Property" />
  <reg:name xml:lang="en">relatedWork</reg:name>
  <rdfs:label xml:lang="en">has related work</rdfs:label>
  <reg:lexicalAlias rdf:resource="http://rdaregistry.info/Elements/x/datatype/relatedWork.en" />
  <rdfs:domain rdf:resource="http://rdaregistry.info/Elements/c/C10013" />
  <rdfs:subPropertyOf rdf:resource="http://rdaregistry.info/Elements/x/datatype/P00001" />
</rdf:Description>


<!-- Status properties used in this document  -->
    <skos:Concept rdf:about="http://metadataregistry.org/uri/RegStatus/1001">
        <skos:prefLabel xml:lang="en">Published</skos:prefLabel>
    </skos:Concept>
</rdf:RDF>
