<?xml version="1.0" encoding = "UTF-8"?>
<rdf:RDF
    xmlns:dc="http://purl.org/dc/elements/1.1/"
    xmlns:rdakit="http://metadataregistry.org/uri/profile/rdakit/"
    xmlns:rdf="http://www.w3.org/1999/02/22-rdf-syntax-ns#"
    xmlns:reg="http://metadataregistry.org/uri/profile/regap/"
    xmlns:skos="http://www.w3.org/2004/02/skos/core#">

<!-- Scheme: RDA File Type -->
    <skos:ConceptScheme rdf:about="http://rdaregistry.info/termList/fileType">
        <dc:title>RDA File Type</dc:title>
    </skos:ConceptScheme>

<!-- Concept: audio file  -->
    <skos:Concept rdf:about="http://rdaregistry.info/termList/fileType1001" xml:lang="en">
      <skos:inScheme rdf:resource="http://rdaregistry.info/termList/fileType"/>
      <reg:status rdf:resource="http://metadataregistry.org/uri/RegStatus/1001"/>
      <reg:identifier rdf:resource="http://metadataregistry.org/concepts/1116"/>
      <skos:prefLabel xml:lang="en">audio file</skos:prefLabel>
      <rdakit:toolkitLabel xml:lang="en">audio file</rdakit:toolkitLabel>
      <skos:definition xml:lang="en">A file type for storing electronically recorded audio content.</skos:definition>
      <rdakit:toolkitDefinition xml:lang="en">A file type for storing electronically recorded audio content.</rdakit:toolkitDefinition>
    </skos:Concept>
<!-- Concept: data file  -->
    <skos:Concept rdf:about="http://rdaregistry.info/termList/fileType1005" xml:lang="en">
      <skos:inScheme rdf:resource="http://rdaregistry.info/termList/fileType"/>
      <reg:status rdf:resource="http://metadataregistry.org/uri/RegStatus/1001"/>
      <reg:identifier rdf:resource="http://metadataregistry.org/concepts/1120"/>
      <skos:prefLabel xml:lang="en">data file</skos:prefLabel>
      <rdakit:toolkitLabel xml:lang="en">data file</rdakit:toolkitLabel>
      <skos:definition xml:lang="en">A file type for storing electronically recorded content representing data values.</skos:definition>
      <rdakit:toolkitDefinition xml:lang="en">A file type for storing electronically recorded content representing data values.</rdakit:toolkitDefinition>
    </skos:Concept>
<!-- Concept: image file  -->
    <skos:Concept rdf:about="http://rdaregistry.info/termList/fileType1004" xml:lang="en">
      <skos:inScheme rdf:resource="http://rdaregistry.info/termList/fileType"/>
      <reg:status rdf:resource="http://metadataregistry.org/uri/RegStatus/1001"/>
      <reg:identifier rdf:resource="http://metadataregistry.org/concepts/1119"/>
      <skos:prefLabel xml:lang="en">image file</skos:prefLabel>
      <rdakit:toolkitLabel xml:lang="en">image file</rdakit:toolkitLabel>
      <skos:definition xml:lang="en">A file type for storing electronically recorded content representing still images.</skos:definition>
      <rdakit:toolkitDefinition xml:lang="en">A file type for storing electronically recorded content representing still images.</rdakit:toolkitDefinition>
    </skos:Concept>
<!-- Concept: program file  -->
    <skos:Concept rdf:about="http://rdaregistry.info/termList/fileType1003" xml:lang="en">
      <skos:inScheme rdf:resource="http://rdaregistry.info/termList/fileType"/>
      <reg:status rdf:resource="http://metadataregistry.org/uri/RegStatus/1001"/>
      <reg:identifier rdf:resource="http://metadataregistry.org/concepts/1118"/>
      <skos:prefLabel xml:lang="en">program file</skos:prefLabel>
      <rdakit:toolkitLabel xml:lang="en">program file</rdakit:toolkitLabel>
      <skos:definition xml:lang="en">A file type for storing electronically recorded programs consisting of organized lists of instructions to be executed by computer software.</skos:definition>
      <rdakit:toolkitDefinition xml:lang="en">A file type for storing electronically recorded programs consisting of organized lists of instructions to be executed by computer software.</rdakit:toolkitDefinition>
    </skos:Concept>
<!-- Concept: text file  -->
    <skos:Concept rdf:about="http://rdaregistry.info/termList/fileType1002" xml:lang="en">
      <skos:inScheme rdf:resource="http://rdaregistry.info/termList/fileType"/>
      <reg:status rdf:resource="http://metadataregistry.org/uri/RegStatus/1001"/>
      <reg:identifier rdf:resource="http://metadataregistry.org/concepts/1117"/>
      <skos:prefLabel xml:lang="en">text file</skos:prefLabel>
      <rdakit:toolkitLabel xml:lang="en">text file</rdakit:toolkitLabel>
      <skos:definition xml:lang="en">A file type for storing electronically recorded textual content.</skos:definition>
      <rdakit:toolkitDefinition xml:lang="en">A file type for storing electronically recorded textual content.</rdakit:toolkitDefinition>
    </skos:Concept>
<!-- Concept: video file  -->
    <skos:Concept rdf:about="http://rdaregistry.info/termList/fileType1006" xml:lang="en">
      <skos:inScheme rdf:resource="http://rdaregistry.info/termList/fileType"/>
      <reg:status rdf:resource="http://metadataregistry.org/uri/RegStatus/1001"/>
      <reg:identifier rdf:resource="http://metadataregistry.org/concepts/1121"/>
      <skos:prefLabel xml:lang="en">video file</skos:prefLabel>
      <rdakit:toolkitLabel xml:lang="en">video file</rdakit:toolkitLabel>
      <skos:definition xml:lang="en">A file type for storing electronically recorded content representing moving images.</skos:definition>
      <rdakit:toolkitDefinition xml:lang="en">A file type for storing electronically recorded content representing moving images.</rdakit:toolkitDefinition>
    </skos:Concept>

<!-- Status properties used in this document  -->
    <skos:Concept rdf:about="http://metadataregistry.org/uri/RegStatus/1001">
        <skos:prefLabel xml:lang="en">Published</skos:prefLabel>
    </skos:Concept>

</rdf:RDF>
